uncoil/__init__.py
uncoil/__main__.py
uncoil/config/__init__.py
uncoil/config/hard_ignore.py
uncoil/config/soft_ignore.py
uncoil-1.3.0.dist-info/METADATA
uncoil-1.3.0.dist-info/WHEEL
uncoil-1.3.0.dist-info/entry_points.txt
uncoil-1.3.0.dist-info/licenses/LICENSE
uncoil-1.3.0.dist-info/RECORD
