Metadata-Version: 2.4
Name: uncoil
Version: 1.3.0
Summary: A command-line tool to explore and print contents of directories with options to skip certain patterns.
Author-email: "Matthew J. Thompson" <thompson.m.j@outlook.com>
License: MIT License
License-File: LICENSE
Requires-Python: >=3.8
Requires-Dist: jupytext
Requires-Dist: rich>=13.6.0
Provides-Extra: dev
Requires-Dist: ipykernel; extra == 'dev'
Requires-Dist: ipynb; extra == 'dev'
Requires-Dist: nbformat; extra == 'dev'
Requires-Dist: pre-commit; extra == 'dev'
Requires-Dist: pytest; extra == 'dev'
Requires-Dist: ruff; extra == 'dev'
